ms_fabric_mcp_server/__init__.py
ms_fabric_mcp_server/__main__.py
ms_fabric_mcp_server/cli.py
ms_fabric_mcp_server/server.py
ms_fabric_mcp_server/client/__init__.py
ms_fabric_mcp_server/client/config.py
ms_fabric_mcp_server/client/exceptions.py
ms_fabric_mcp_server/client/http_client.py
ms_fabric_mcp_server/models/__init__.py
ms_fabric_mcp_server/models/item.py
ms_fabric_mcp_server/models/job.py
ms_fabric_mcp_server/models/lakehouse.py
ms_fabric_mcp_server/models/results.py
ms_fabric_mcp_server/models/semantic_model.py
ms_fabric_mcp_server/models/workspace.py
ms_fabric_mcp_server/services/__init__.py
ms_fabric_mcp_server/services/item.py
ms_fabric_mcp_server/services/job.py
ms_fabric_mcp_server/services/livy.py
ms_fabric_mcp_server/services/notebook.py
ms_fabric_mcp_server/services/pipeline.py
ms_fabric_mcp_server/services/powerbi.py
ms_fabric_mcp_server/services/semantic_model.py
ms_fabric_mcp_server/services/sql.py
ms_fabric_mcp_server/services/workspace.py
ms_fabric_mcp_server/tools/__init__.py
ms_fabric_mcp_server/tools/base.py
ms_fabric_mcp_server/tools/item_tools.py
ms_fabric_mcp_server/tools/job_tools.py
ms_fabric_mcp_server/tools/livy_tools.py
ms_fabric_mcp_server/tools/notebook_tools.py
ms_fabric_mcp_server/tools/pipeline_tools.py
ms_fabric_mcp_server/tools/powerbi_tools.py
ms_fabric_mcp_server/tools/semantic_model_tools.py
ms_fabric_mcp_server/tools/sql_tools.py
ms_fabric_mcp_server/tools/workspace_tools.py
ms_fabric_mcp_server-0.7.0.dist-info/METADATA
ms_fabric_mcp_server-0.7.0.dist-info/WHEEL
ms_fabric_mcp_server-0.7.0.dist-info/entry_points.txt
ms_fabric_mcp_server-0.7.0.dist-info/RECORD
