Metadata-Version: 2.4
Name: ms-fabric-mcp-server
Version: 0.7.0
Summary: Model Context Protocol (MCP) server for Microsoft Fabric - exposes Fabric operations as MCP tools for AI agents
Author: Microsoft
License: MIT
Keywords: agent,ai,fabric,fastmcp,llm,mcp,microsoft-fabric
Classifier: Development Status :: 4 - Beta
Classifier: Intended Audience :: Developers
Classifier: License :: OSI Approved :: MIT License
Classifier: Programming Language :: Python :: 3
Classifier: Programming Language :: Python :: 3.11
Classifier: Programming Language :: Python :: 3.12
Classifier: Programming Language :: Python :: 3.13
Requires-Python: >=3.11
Requires-Dist: azure-identity>=1.23.0
Requires-Dist: fastmcp>=2.10.0
Requires-Dist: pydantic>=2.0.0
Requires-Dist: python-dotenv>=1.0.0
Requires-Dist: requests>=2.25.0
Provides-Extra: dev
Requires-Dist: bandit[toml]>=1.7.5; extra == 'dev'
Requires-Dist: black>=23.0.0; extra == 'dev'
Requires-Dist: isort>=5.13.0; extra == 'dev'
Requires-Dist: pytest-asyncio>=0.21.0; extra == 'dev'
Requires-Dist: pytest-cov>=4.0.0; extra == 'dev'
Requires-Dist: pytest-mock>=3.10.0; extra == 'dev'
Requires-Dist: pytest>=7.0.0; extra == 'dev'
Requires-Dist: responses>=0.23.0; extra == 'dev'
Provides-Extra: sql
Requires-Dist: pyodbc>=5.0.0; extra == 'sql'
Provides-Extra: telemetry
Requires-Dist: opentelemetry-api>=1.20.0; extra == 'telemetry'
Requires-Dist: opentelemetry-instrumentation-dbapi>=0.46b0; extra == 'telemetry'
